 {"id": "gh-premium-1769148718508-102", "styles": {"properties": {"width": "fit-content", "padding": "100px 80px", "minWidth": "200px", "minHeight": "100px"}}, "content": "", "tagName": "section", "children": [{"id": "gh-premium-1769148718508-101", "styles": {"properties": {"margin": "0 auto", "display": "flex", "maxWidth": "1200px", "alignItems": "center", "flexDirection": "column"}}, "content": "", "tagName": "div", "children": [{"id": "gh-premium-1769148718508-39", "styles": {"properties": {"width": "100%", "display": "flex", "alignItems": "flex-start", "marginBottom": "48px", "flexDirection": "column"}}, "content": "", "tagName": "div", "children": [{"id": "gh-premium-1769148718508-37", "styles": {"properties": {"color": "#D29F66", "fontSize": "12px", "marginBottom": "16px", "letterSpacing": "3px", "textTransform": "uppercase"}}, "content": "╨Ъ╨░╤В╨░╨╗╨╛╨│", "tagName": "p", "children": [], "metadata": {"name": "Projects Label"}, "attributes": {}, "elementType": "text"}, {"id": "gh-premium-1769148718508-38", "styles": {"properties": {"color": "#1A1A1A", "fontSize": "36px", "fontWeight": "300", "letterSpacing": "-1px"}}, "content": "╨Э╨░╤И╨╕ ╨╢╨╕╨╗╤Л╨╡ ╨║╨╛╨╝╨┐╨╗╨╡╨║╤Б╤Л", "tagName": "h2", "children": [], "metadata": {"name": "Projects Title"}, "attributes": {}, "elementType": "text"}], "metadata": {"name": "Projects Header"}, "attributes": {}, "elementType": "container"}, {"id": "gh-premium-1769148718508-59", "styles": {"properties": {"gap": "32px", "width": "100%", "display": "flex", "flexWrap": "wrap", "alignItems": "flex-start", "marginBottom": "32px", "justifyContent": "flex-start"}}, "content": "", "tagName": "div", "children": [{"id": "gh-premium-1769148718508-46", "styles": {"properties": {}}, "content": "", "tagName": "div", "children": [{"id": "gh-premium-1769148718508-40", "styles": {"properties": {"color": "#8A8A8A", "display": "block", "fontSize": "13px", "marginBottom": "8px"}}, "content": "╨Т╤Л╨▒╨╡╤А╨╕╤В╨╡ ╨╗╨╛╨║╨░╤Ж╨╕╤О", "tagName": "label", "children": [], "metadata": {"name": "Location Label"}, "attributes": {}, "elementType": "text"}, {"id": "gh-premium-1769148718508-45", "styles": {"properties": {"border": "1px solid #E8E8E8", "cursor": "pointer", "padding": "14px 48px 14px 16px", "fontSize": "15px", "minWidth": "240px", "borderRadius": "4px", "backgroundColor": "#FFFFFF"}}, "content": "", "tagName": "select", "children": [{"id": "gh-premium-1769148718508-41", "styles": {"properties": {}}, "content": "╨а╨░╨╣╨╛╨╜, ╨╝╨╡╤В╤А╨╛", "tagName": "option", "children": [], "metadata": {"name": "Default Location"}, "attributes": {}, "elementType": "option"}, {"id": "gh-premium-1769148718508-42", "styles": {"properties": {}}, "content": "╨о╨╜╤Г╤Б╨░╨▒╨░╨┤", "tagName": "option", "children": [], "metadata": {"name": "Location 1"}, "attributes": {}, "elementType": "option"}, {"id": "gh-premium-1769148718508-43", "styles": {"properties": {}}, "content": "╨Ь╨╕╤А╨╖╨╛ ╨г╨╗╤Г╨│╨▒╨╡╨║", "tagName": "option", "children": [], "metadata": {"name": "Location 2"}, "attributes": {}, "elementType": "option"}, {"id": "gh-premium-1769148718508-44", "styles": {"properties": {}}, "content": "╨з╨╕╨╗╨░╨╜╨╖╨░╤А", "tagName": "option", "children": [], "metadata": {"name": "Location 3"}, "attributes": {}, "elementType": "option"}], "metadata": {"name": "Location Select"}, "attributes": {}, "elementType": "select"}], "metadata": {"name": "Location Filter"}, "attributes": {}, "elementType": "container"}, {"id": "gh-premium-1769148718508-52", "styles": {"properties": {"flex": "1", "maxWidth": "300px"}}, "content": "", "tagName": "div", "children": [{"id": "gh-premium-1769148718508-47", "styles": {"properties": {"color": "#8A8A8A", "display": "block", "fontSize": "13px", "marginBottom": "8px"}}, "content": "╨б╤В╨╛╨╕╨╝╨╛╤Б╤В╤М, $", "tagName": "label", "children": [], "metadata": {"name": "Price Label"}, "attributes": {}, "elementType": "text"}, {"id": "gh-premium-1769148718508-51", "styles": {"properties": {"gap": "16px", "display": "flex", "alignItems": "center"}}, "content": "", "tagName": "div", "children": [{"id": "gh-premium-1769148718508-48", "styles": {"properties": {"width": "120px", "border": "1px solid #E8E8E8", "padding": "14px 16px", "fontSize": "15px", "borderRadius": "4px", "backgroundColor": "#ffffff"}}, "content": "", "tagName": "input", "children": [], "metadata": {"name": "Price From"}, "attributes": {"type": "text", "placeholder": "╨╛╤В 50 000"}, "elementType": "input"}, {"id": "gh-premium-1769148718508-49", "styles": {"properties": {"color": "#8A8A8A"}}, "content": "тАФ", "tagName": "span", "children": [], "metadata": {"name": "Separator"}, "attributes": {}, "elementType": "text"}, {"id": "gh-premium-1769148718508-50", "styles": {"properties": {"width": "120px", "border": "1px solid #E8E8E8", "padding": "14px 16px", "fontSize": "15px", "borderRadius": "4px", "backgroundColor": "#ffffff"}}, "content": "", "tagName": "input", "children": [], "metadata": {"name": "Price To"}, "attributes": {"type": "text", "placeholder": "╨┤╨╛ 500 000"}, "elementType": "input"}], "metadata": {"name": "Price Inputs Container"}, "attributes": {}, "elementType": "container"}], "metadata": {"name": "Price Range Filter"}, "attributes": {}, "elementType": "container"}, {"id": "gh-premium-1769148718508-58", "styles": {"properties": {}}, "content": "", "tagName": "div", "children": [{"id": "gh-premium-1769148718508-53", "styles": {"properties": {"color": "#8A8A8A", "display": "block", "fontSize": "13px", "marginBottom": "8px"}}, "content": "╨Ф╨░╤В╨░ ╤Б╨┤╨░╤З╨╕ ╨┤╨╛", "tagName": "label", "children": [], "metadata": {"name": "Year Label"}, "attributes": {}, "elementType": "text"}, {"id": "gh-premium-1769148718508-57", "styles": {"properties": {"gap": "8px", "display": "flex"}}, "content": "", "tagName": "div", "children": [{"id": "gh-premium-1769148718508-54", "styles": {"properties": {"color": "#1A1A1A", "border": "1px solid #D29F66", "cursor": "pointer", "padding": "12px 20px", "fontSize": "14px", "fontWeight": "400", "borderRadius": "4px", "backgroundColor": "rgba(210,159,102,0.1)"}}, "content": "2026", "tagName": "button", "children": [], "metadata": {"name": "Year 2026"}, "attributes": {}, "elementType": "button"}, {"id": "gh-premium-1769148718508-55", "styles": {"properties": {"color": "#1A1A1A", "border": "1px solid #E8E8E8", "cursor": "pointer", "padding": "12px 20px", "fontSize": "14px", "fontWeight": "400", "borderRadius": "4px", "backgroundColor": "#FFFFFF"}}, "content": "2027", "tagName": "button", "children": [], "metadata": {"name": "Year 2027"}, "attributes": {}, "elementType": "button"}, {"id": "gh-premium-1769148718508-56", "styles": {"properties": {"color": "#1A1A1A", "border": "1px solid #E8E8E8", "cursor": "pointer", "padding": "12px 20px", "fontSize": "14px", "fontWeight": "400", "borderRadius": "4px", "backgroundColor": "#FFFFFF"}}, "content": "2028", "tagName": "button", "children": [], "metadata": {"name": "Year 2028"}, "attributes": {}, "elementType": "button"}], "metadata": {"name": "Year Buttons"}, "attributes": {}, "elementType": "container"}], "metadata": {"name": "Year Filter"}, "attributes": {}, "elementType": "container"}], "metadata": {"name": "Filter Header"}, "attributes": {}, "elementType": "container"}, {"id": "gh-premium-1769148718508-65", "styles": {"properties": {"gap": "12px", "width": "100%", "display": "flex", "flexWrap": "wrap", "alignItems": "center", "marginBottom": "48px", "justifyContent": "flex-start"}}, "content": "", "tagName": "div", "children": [{"id": "gh-premium-1769148718508-60", "styles": {"properties": {"color": "#FFFFFF", "border": "1px solid #D29F66", "cursor": "pointer", "padding": "10px 24px", "fontSize": "14px", "fontWeight": "400", "borderRadius": "4px", "backgroundColor": "#D29F66"}}, "content": "╨Т╤Б╨╡", "tagName": "button", "children": [], "metadata": {"name": "Filter ╨Т╤Б╨╡"}, "attributes": {}, "elementType": "button"}, {"id": "gh-premium-1769148718508-61", "styles": {"properties": {"color": "#4A4A4A", "border": "1px solid #E8E8E8", "cursor": "pointer", "padding": "10px 24px", "fontSize": "14px", "fontWeight": "400", "borderRadius": "4px", "backgroundColor": "#FFFFFF"}}, "content": "╨б ╨║╨╗╤О╤З╨░╨╝╨╕", "tagName": "button", "children": [], "metadata": {"name": "Filter ╨б ╨║╨╗╤О╤З╨░╨╝╨╕"}, "attributes": {}, "elementType": "button"}, {"id": "gh-premium-1769148718508-62", "styles": {"properties": {"color": "#4A4A4A", "border": "1px solid #E8E8E8", "cursor": "pointer", "padding": "10px 24px", "fontSize": "14px", "fontWeight": "400", "borderRadius": "4px", "backgroundColor": "#FFFFFF"}}, "content": "╨С╨╕╨╖╨╜╨╡╤Б-╨║╨╗╨░╤Б╤Б", "tagName": "button", "children": [], "metadata": {"name": "Filter ╨С╨╕╨╖╨╜╨╡╤Б-╨║╨╗╨░╤Б╤Б"}, "attributes": {}, "elementType": "button"}, {"id": "gh-premium-1769148718508-63", "styles": {"properties": {"color": "#4A4A4A", "border": "1px solid #E8E8E8", "cursor": "pointer", "padding": "10px 24px", "fontSize": "14px", "fontWeight": "400", "borderRadius": "4px", "backgroundColor": "#FFFFFF"}}, "content": "╨Я╤А╨╡╨╝╨╕╤Г╨╝", "tagName": "button", "children": [], "metadata": {"name": "Filter ╨Я╤А╨╡╨╝╨╕╤Г╨╝"}, "attributes": {}, "elementType": "button"}], "metadata": {"name": "Tag Filters"}, "attributes": {}, "elementType": "container"}, {"id": "1769405707337_unm4vedmb", "styles": {"properties": {"gap": "32px", "width": "100%", "display": "grid", "minWidth": "200px", "minHeight": "100px", "gridTemplateRows": "repeat(2, 1fr)", "gridTemplateColumns": "repeat(3, 1fr)"}}, "content": "", "tagName": "div", "children": [], "metadata": {"name": "Projects Grid", "locked": false, "linkedBlockId": "3e783825-530d-4ef3-b567-2540e97a7944"}, "attributes": {}, "elementType": "container"}], "metadata": {"name": "Projects Container"}, "attributes": {}, "variations": {"desktop-fhd": {"inheritedOverrides": {"1769405707337_unm4vedmb": {"styles": {"gridTemplateRows": "repeat(2, 1fr)", "gridTemplateColumns": "repeat(3, 1fr)"}}}}}, "elementType": "container"}], "metadata": {"name": "Projects Section"}, "attributes": {}, "elementType": "container"}

